easyarg/__init__.py
easyarg/__main__.py
easyarg/easyarg.py
easyarg/libargparse.py
easyarg/liblogging.py
rdee_easyarg-25.4.10.dist-info/entry_points.txt
rdee_easyarg-25.4.10.dist-info/LICENSE
rdee_easyarg-25.4.10.dist-info/WHEEL
rdee_easyarg-25.4.10.dist-info/METADATA
rdee_easyarg-25.4.10.dist-info/RECORD
