Metadata-Version: 2.3
Name: rdee-easyarg
Version: 25.4.10
Summary: rdee-series toolkits: python-easyarg
Author-email: Roadelse <roadelse@qq.com>
Classifier: License :: OSI Approved :: MIT License
Requires-Dist: argcomplete
Requires-Dist: rich
Project-URL: Home, https://github.com/Roadelse/rdee-python-easyarg
